project_utilities/__init__.py
project_utilities/file_utils.py
project_utilities/make_release.py
project_utilities/project_init.py
project_utilities-1.0.2.dist-info/LICENSE
project_utilities-1.0.2.dist-info/METADATA
project_utilities-1.0.2.dist-info/WHEEL
project_utilities-1.0.2.dist-info/top_level.txt
project_utilities-1.0.2.dist-info/RECORD
