Metadata-Version: 2.1
Name: project-utilities
Version: 1.0.2
Summary: A package containing scripts, classes, functions etc all useful for maintaining projects
Home-page: https://github.com/RickarySanchez/project-utilities
Author: RickarySanchez
Author-email: RickarySanchez@gmail.com
License: MIT
Platform: UNKNOWN
Classifier: License :: OSI Approved :: MIT License
Classifier: Programming Language :: Python :: 3.9
License-File: LICENSE
Requires-Dist: PyYAML
